CHANGES.txt
README.txt
bootstrap.py
buildout.cfg
setup.py
src/z3c/__init__.py
src/z3c.recipe.fakezope2eggs.egg-info/PKG-INFO
src/z3c.recipe.fakezope2eggs.egg-info/SOURCES.txt
src/z3c.recipe.fakezope2eggs.egg-info/dependency_links.txt
src/z3c.recipe.fakezope2eggs.egg-info/entry_points.txt
src/z3c.recipe.fakezope2eggs.egg-info/namespace_packages.txt
src/z3c.recipe.fakezope2eggs.egg-info/not-zip-safe
src/z3c.recipe.fakezope2eggs.egg-info/requires.txt
src/z3c.recipe.fakezope2eggs.egg-info/top_level.txt
src/z3c/recipe/__init__.py
src/z3c/recipe/fakezope2eggs/README.txt
src/z3c/recipe/fakezope2eggs/__init__.py
src/z3c/recipe/fakezope2eggs/tests/__init__.py
src/z3c/recipe/fakezope2eggs/tests/test_docs.py