Metadata-Version: 1.0
Name: z3c.recipe.fakezope2eggs
Version: 0.5
Summary: ZC Buildout recipe to fake zope 2 packages as eggs.
Home-page: http://svn.zope.org/z3c.recipe.fakezope2eggs
Author: Jean-Francois Roche
Author-email: jfroche@affinitic.be
License: ZPL 2.1
Keywords: zope2 buildout
Platform: UNKNOWN
Classifier: License :: OSI Approved :: Zope Public License
Classifier: Framework :: Buildout
Classifier: Framework :: Plone
Classifier: Framework :: Zope2
Classifier: Programming Language :: Python
